{
  "displayFieldName": "CRIMEGRID",
  "fieldAliases": {"CRIMEGRID": "CRIMEGRID"},
  "geometryType": "esriGeometryPolygon",
  "spatialReference": {"wkid": 102113},
  "features": [{
    "attributes": {"CRIMEGRID": "120214"},
    "geometry": {"rings": [[
      [
        -8404943.0655,
        4743935.901900001
      ],
      [
        -8404932.5669,
        4743920.546499997
      ],
      [
        -8404886.2174,
        4743849.924900003
      ],
      [
        -8404823.0013,
        4743753.0945999995
      ],
      [
        -8404568.7054,
        4743371.477300003
      ],
      [
        -8404513.0123,
        4743287.512000002
      ],
      [
        -8404819.4202,
        4743086.2469
      ],
      [
        -8404901.9681,
        4743032.378700003
      ],
      [
        -8404938.6657,
        4743007.423500001
      ],
      [
        -8404955.6335,
        4743034.782300003
      ],
      [
        -8405016.5121,
        4743131.021300003
      ],
      [
        -8405076.481,
        4743222.2918
      ],
      [
        -8405158.1156,
        4743347.897699997
      ],
      [
        -8405225.7469,
        4743452.728600003
      ],
      [
        -8405274.9198,
        4743529.535099998
      ],
      [
        -8405358.7355,
        4743657.909000002
      ],
      [
        -8405308.7658,
        4743693.618900001
      ],
      [
        -8405167.3562,
        4743789.152500004
      ],
      [
        -8404943.3273,
        4743936.2754999995
      ],
      [
        -8404943.0655,
        4743935.901900001
      ]
    ]]}
  }]
}